vtf2img/__init__.py
vtf2img/__main__.py
vtf2img/buffer.py
vtf2img/cli.py
vtf2img/header.py
vtf2img/parser.py
vtf2img/image_formats/__init__.py
vtf2img/image_formats/abgr8888.py
vtf2img/image_formats/abstract_format.py
vtf2img/image_formats/argb8888.py
vtf2img/image_formats/bgr888.py
vtf2img/image_formats/bgra8888.py
vtf2img/image_formats/dxt1.py
vtf2img/image_formats/dxt5.py
vtf2img/image_formats/rgb888.py
vtf2img/image_formats/rgba8888.py
vtf2img-0.1.0.dist-info/LICENSE
vtf2img-0.1.0.dist-info/METADATA
vtf2img-0.1.0.dist-info/WHEEL
vtf2img-0.1.0.dist-info/entry_points.txt
vtf2img-0.1.0.dist-info/top_level.txt
vtf2img-0.1.0.dist-info/RECORD
