Metadata-Version: 2.1
Name: vtf2img
Version: 0.1.0
Summary: A library to convert Valve Texture Format (VTF) files into images
Home-page: https://github.com/julienc91/vtf2img/
Author: Julien Chaumont
Author-email: vtf2img@julienc.io
License: MIT
Platform: UNKNOWN
Classifier: License :: OSI Approved :: MIT License
Classifier: Programming Language :: Python :: 3
Classifier: Programming Language :: Python :: 3.7
Requires-Dist: Pillow
